DaxingWangzhanJiagouXuexiBiji/README.md
DaxingWangzhanJiagouXuexiBiji/__init__.py
DaxingWangzhanJiagouXuexiBiji/__main__.py
DaxingWangzhanJiagouXuexiBiji/file.epub
DaxingWangzhanJiagouXuexiBiji/index.html
DaxingWangzhanJiagouXuexiBiji/css/__init__.py
DaxingWangzhanJiagouXuexiBiji/css/annotations.css
DaxingWangzhanJiagouXuexiBiji/css/main.css
DaxingWangzhanJiagouXuexiBiji/css/normalize.css
DaxingWangzhanJiagouXuexiBiji/css/popup.css
DaxingWangzhanJiagouXuexiBiji/font/__init__.py
DaxingWangzhanJiagouXuexiBiji/font/fontello.eot
DaxingWangzhanJiagouXuexiBiji/font/fontello.svg
DaxingWangzhanJiagouXuexiBiji/font/fontello.ttf
DaxingWangzhanJiagouXuexiBiji/font/fontello.woff
DaxingWangzhanJiagouXuexiBiji/img/__init__.py
DaxingWangzhanJiagouXuexiBiji/img/annotator-glyph-sprite.png
DaxingWangzhanJiagouXuexiBiji/img/annotator-icon-sprite.png
DaxingWangzhanJiagouXuexiBiji/img/apple-touch-icon.png
DaxingWangzhanJiagouXuexiBiji/img/cancelfullscreen.png
DaxingWangzhanJiagouXuexiBiji/img/close.png
DaxingWangzhanJiagouXuexiBiji/img/fullscreen.png
DaxingWangzhanJiagouXuexiBiji/img/loader.gif
DaxingWangzhanJiagouXuexiBiji/img/menu-icon.png
DaxingWangzhanJiagouXuexiBiji/img/save.png
DaxingWangzhanJiagouXuexiBiji/img/saved.png
DaxingWangzhanJiagouXuexiBiji/img/settings-s.png
DaxingWangzhanJiagouXuexiBiji/img/settings.png
DaxingWangzhanJiagouXuexiBiji/img/star.png
DaxingWangzhanJiagouXuexiBiji/js/__init__.py
DaxingWangzhanJiagouXuexiBiji/js/epub.js
DaxingWangzhanJiagouXuexiBiji/js/epub.min.js
DaxingWangzhanJiagouXuexiBiji/js/epub.min.map
DaxingWangzhanJiagouXuexiBiji/js/hooks.min.js
DaxingWangzhanJiagouXuexiBiji/js/hooks.min.map
DaxingWangzhanJiagouXuexiBiji/js/reader.js
DaxingWangzhanJiagouXuexiBiji/js/reader.js.map
DaxingWangzhanJiagouXuexiBiji/js/reader.min.js
DaxingWangzhanJiagouXuexiBiji/js/reader.min.map
DaxingWangzhanJiagouXuexiBiji/js/hooks/__init__.py
DaxingWangzhanJiagouXuexiBiji/js/hooks/extensions/__init__.py
DaxingWangzhanJiagouXuexiBiji/js/hooks/extensions/highlight.js
daxing_wangzhan_jiagou_xuexi_biji-2024.3.1.0.dist-info/METADATA
daxing_wangzhan_jiagou_xuexi_biji-2024.3.1.0.dist-info/WHEEL
daxing_wangzhan_jiagou_xuexi_biji-2024.3.1.0.dist-info/entry_points.txt
daxing_wangzhan_jiagou_xuexi_biji-2024.3.1.0.dist-info/top_level.txt
daxing_wangzhan_jiagou_xuexi_biji-2024.3.1.0.dist-info/RECORD
